speechall/__init__.py
speechall/client.py
speechall/environment.py
speechall/core/__init__.py
speechall/core/api_error.py
speechall/core/client_wrapper.py
speechall/core/datetime_utils.py
speechall/core/file.py
speechall/core/force_multipart.py
speechall/core/http_client.py
speechall/core/http_response.py
speechall/core/jsonable_encoder.py
speechall/core/pydantic_utilities.py
speechall/core/query_encoder.py
speechall/core/remove_none_from_dict.py
speechall/core/request_options.py
speechall/core/serialization.py
speechall/errors/__init__.py
speechall/errors/bad_request_error.py
speechall/errors/gateway_timeout_error.py
speechall/errors/internal_server_error.py
speechall/errors/not_found_error.py
speechall/errors/payment_required_error.py
speechall/errors/service_unavailable_error.py
speechall/errors/too_many_requests_error.py
speechall/errors/unauthorized_error.py
speechall/replacement_rules/__init__.py
speechall/replacement_rules/client.py
speechall/replacement_rules/raw_client.py
speechall/replacement_rules/types/__init__.py
speechall/replacement_rules/types/create_replacement_ruleset_response.py
speechall/speech_to_text/__init__.py
speechall/speech_to_text/client.py
speechall/speech_to_text/raw_client.py
speechall/types/__init__.py
speechall/types/base_transcription_configuration.py
speechall/types/error_response.py
speechall/types/exact_rule.py
speechall/types/regex_group_rule.py
speechall/types/regex_group_rule_flags_item.py
speechall/types/regex_rule.py
speechall/types/regex_rule_flags_item.py
speechall/types/replacement_rule.py
speechall/types/speech_to_text_model.py
speechall/types/speech_to_text_model_accuracy_tier.py
speechall/types/speech_to_text_model_model_type.py
speechall/types/transcript_language_code.py
speechall/types/transcript_output_format.py
speechall/types/transcription_detailed.py
speechall/types/transcription_model_identifier.py
speechall/types/transcription_only_text.py
speechall/types/transcription_provider.py
speechall-0.3.0.dist-info/METADATA
speechall-0.3.0.dist-info/WHEEL
speechall-0.3.0.dist-info/top_level.txt
speechall-0.3.0.dist-info/RECORD
