Metadata-Version: 2.4
Name: speechall
Version: 0.3.0
Summary: Python SDK for Speechall API - Speech-to-text transcription service
Author: Speechall
License: MIT
Project-URL: Homepage, https://github.com/speechall/speechall-python-sdk
Project-URL: Documentation, https://docs.speechall.com
Project-URL: Repository, https://github.com/speechall/speechall-python-sdk
Keywords: speechall,speech-to-text,transcription,api,sdk
Classifier: Development Status :: 4 - Beta
Classifier: Intended Audience :: Developers
Classifier: Programming Language :: Python :: 3
Classifier: Programming Language :: Python :: 3.8
Classifier: Programming Language :: Python :: 3.9
Classifier: Programming Language :: Python :: 3.10
Classifier: Programming Language :: Python :: 3.11
Classifier: Programming Language :: Python :: 3.12
Classifier: Topic :: Software Development :: Libraries :: Python Modules
Classifier: Topic :: Multimedia :: Sound/Audio :: Speech
Requires-Python: >=3.8
Requires-Dist: httpx>=0.27.0
Requires-Dist: pydantic>=2.0.0
Requires-Dist: typing-extensions>=4.0.0
Provides-Extra: dev
Requires-Dist: pytest>=7.0.0; extra == "dev"
Requires-Dist: pytest-asyncio>=0.21.0; extra == "dev"
Requires-Dist: mypy>=1.0.0; extra == "dev"
